{
  "currency": 83550,
  "tick": 3957,
  "mutation_stats": {
    "attempted": 3957,
    "success": 1672
  },
  "recent_events": [
    "STABLE: 'Verdant Rapier of Torment' did not mutate this tick.",
    "MUTATED: 'Glacial Focus of Sparks' evolved to generation 18.",
    "STABLE: 'Searing Spear of Judgement' did not mutate this tick.",
    "STABLE: 'Titanic Blade of Stone' did not mutate this tick.",
    "STABLE: 'Titanic Blade of Stone' did not mutate this tick.",
    "STABLE: 'Glacial Focus of Sparks' did not mutate this tick.",
    "STABLE: 'Resolute Rapier of Iron' did not mutate this tick.",
    "STABLE: 'Glacial Blade of Ash' did not mutate this tick.",
    "MUTATED: 'Searing Spear of Judgement' evolved to generation 14.",
    "STABLE: 'Searing Blade of Venom' did not mutate this tick."
  ],
  "created": 51,
  "avg_lifespan": 38.75609756097561,
  "archived": 41
}