{
  "currency": 0,
  "tick": 57,
  "mutation_stats": {
    "attempted": 57,
    "success": 16
  },
  "recent_events": [
    "STABLE: 'Verdant Relic of Ruins' did not mutate this tick.",
    "STABLE: 'Mundane Rapier of Whispers' did not mutate this tick.",
    "STABLE: 'Glacial Spear of Plagues' did not mutate this tick.",
    "STABLE: 'Glacial Blade of Gales' did not mutate this tick.",
    "STABLE: 'Glacial Spear of Plagues' did not mutate this tick.",
    "STABLE: 'Glacial Blade of Gales' did not mutate this tick.",
    "MUTATED: 'Starlight Shard of Might' evolved to generation 3.",
    "STABLE: 'Verdant Relic of Ruins' did not mutate this tick.",
    "STABLE: 'Verdant Relic of Ruins' did not mutate this tick.",
    "STABLE: 'Dread Rapier of Silence' did not mutate this tick."
  ],
  "created": 10
}