{
  "id": "15be5af7-1645-4456-a35b-ac1b9826c186",
  "name": "Mundane Focus of Carnage",
  "type": "Focus",
  "generation": 37,
  "damage": 42.0,
  "damage_type": [
    "Physical",
    "Magic",
    "Blood"
  ],
  "crit_damage": 2,
  "crit_rate": 0.01,
  "str_mod": 1.6000000000000005,
  "dex_mod": 1.5000000000000004,
  "rarity": 2,
  "durability": 39.39999999999998,
  "max_durability": 101.0,
  "volatility": 0.6,
  "resilience": 0.75,
  "worth": 100,
  "affinities": {
    "Stability": 0.1,
    "Order": 0.1,
    "STR": 0.4,
    "Chaos": 0.1,
    "Scarceness": 0.1,
    "DEX": 0.1
  }
}